WizDriver/WizDriver.py
WizDriver/__init__.py
wiznavigator-0.0.1.dist-info/METADATA
wiznavigator-0.0.1.dist-info/WHEEL
wiznavigator-0.0.1.dist-info/top_level.txt
wiznavigator-0.0.1.dist-info/RECORD
