Metadata-Version: 2.1
Name: wiznavigator
Version: 0.0.1
Summary: A library for navigating between zones and worlds using WizWalker
Home-page: UNKNOWN
Author: wizBots
Author-email: 
License: UNKNOWN
Platform: UNKNOWN
Requires-Python: >=3.8,<4.0
Requires-Dist: lark (<0.12.0,>=0.11.3)
Requires-Dist: wizwalker (>=1.0.0)
Requires-Dist: loguru
Requires-Dist: asyncio
